webint_editor/__init__.py
webint_editor/templates/__init__.py
webint_editor/templates/draft.html
webint_editor/templates/drafts.html
webint_editor/templates/template.html
webint_editor-0.0.176.dist-info/METADATA
webint_editor-0.0.176.dist-info/entry_points.txt
webint_editor-0.0.176.dist-info/WHEEL
webint_editor-0.0.176.dist-info/RECORD
